{
  "actionOverrides": [],
  "activateable": false,
  "childRelationships": [],
  "compactLayoutable": false,
  "createable": true,
  "custom": false,
  "customSetting": false,
  "deletable": true,
  "deprecatedAndHidden": false,
  "feedEnabled": false,
  "fields": [
    {
      "aggregatable": true,
      "autoNumber": false,
      "byteLength": 18,
      "calculated": false,
      "calculatedFormula": null,
      "cascadeDelete": false,
      "caseSensitive": false,
      "controllerName": null,
      "createable": false,
      "custom": false,
      "defaultValue": null,
      "defaultValueFormula": null,
      "defaultedOnCreate": true,
      "dependentPicklist": false,
      "deprecatedAndHidden": false,
      "digits": 0,
      "displayLocationInDecimal": false,
      "encrypted": false,
      "externalId": false,
      "extraTypeInfo": null,
      "filterable": true,
      "filteredLookupInfo": null,
      "groupable": true,
      "highScaleNumber": false,
      "htmlFormatted": false,
      "idLookup": true,
      "inlineHelpText": null,
      "label": "Goal ID",
      "length": 18,
      "mask": null,
      "maskType": null,
      "name": "Id",
      "nameField": false,
      "namePointing": false,
      "nillable": false,
      "permissionable": false,
      "picklistValues": [],
      "precision": 0,
      "queryByDistance": false,
      "referenceTargetField": null,
      "referenceTo": [],
      "relationshipName": null,
      "relationshipOrder": null,
      "restrictedDelete": false,
      "restrictedPicklist": false,
      "scale": 0,
      "soapType": "tns:ID",
      "sortable": true,
      "type": "id",
      "unique": false,
      "updateable": false,
      "writeRequiresMasterRead": false
    },
    {
      "aggregatable": true,
      "autoNumber": false,
      "byteLength": 18,
      "calculated": false,
      "calculatedFormula": null,
      "cascadeDelete": false,
      "caseSensitive": false,
      "controllerName": null,
      "createable": true,
      "custom": false,
      "defaultValue": null,
      "defaultValueFormula": null,
      "defaultedOnCreate": true,
      "dependentPicklist": false,
      "deprecatedAndHidden": false,
      "digits": 0,
      "displayLocationInDecimal": false,
      "encrypted": false,
      "externalId": false,
      "extraTypeInfo": null,
      "filterable": true,
      "filteredLookupInfo": null,
      "groupable": true,
      "highScaleNumber": false,
      "htmlFormatted": false,
      "idLookup": false,
      "inlineHelpText": null,
      "label": "Owner ID",
      "length": 18,
      "mask": null,
      "maskType": null,
      "name": "OwnerId",
      "nameField": false,
      "namePointing": true,
      "nillable": false,
      "permissionable": false,
      "picklistValues": [],
      "precision": 0,
      "queryByDistance": false,
      "referenceTargetField": null,
      "referenceTo": [
        "Group",
        "User"
      ],
      "relationshipName": "Owner",
      "relationshipOrder": null,
      "restrictedDelete": false,
      "restrictedPicklist": false,
      "scale": 0,
      "soapType": "tns:ID",
      "sortable": true,
      "type": "reference",
      "unique": false,
      "updateable": true,
      "writeRequiresMasterRead": false
    },
    {
      "aggregatable": false,
      "autoNumber": false,
      "byteLength": 0,
      "calculated": false,
      "calculatedFormula": null,
      "cascadeDelete": false,
      "caseSensitive": false,
      "controllerName": null,
      "createable": false,
      "custom": false,
      "defaultValue": false,
      "defaultValueFormula": null,
      "defaultedOnCreate": true,
      "dependentPicklist": false,
      "deprecatedAndHidden": false,
      "digits": 0,
      "displayLocationInDecimal": false,
      "encrypted": false,
      "externalId": false,
      "extraTypeInfo": null,
      "filterable": true,
      "filteredLookupInfo": null,
      "groupable": true,
      "highScaleNumber": false,
      "htmlFormatted": false,
      "idLookup": false,
      "inlineHelpText": null,
      "label": "Deleted",
      "length": 0,
      "mask": null,
      "maskType": null,
      "name": "IsDeleted",
      "nameField": false,
      "namePointing": false,
      "nillable": false,
      "permissionable": false,
      "picklistValues": [],
      "precision": 0,
      "queryByDistance": false,
      "referenceTargetField": null,
      "referenceTo": [],
      "relationshipName": null,
      "relationshipOrder": null,
      "restrictedDelete": false,
      "restrictedPicklist": false,
      "scale": 0,
      "soapType": "xsd:boolean",
      "sortable": true,
      "type": "boolean",
      "unique": false,
      "updateable": false,
      "writeRequiresMasterRead": false
    },
    {
      "aggregatable": true,
      "autoNumber": true,
      "byteLength": 765,
      "calculated": false,
      "calculatedFormula": null,
      "cascadeDelete": false,
      "caseSensitive": false,
      "controllerName": null,
      "createable": false,
      "custom": false,
      "defaultValue": null,
      "defaultValueFormula": null,
      "defaultedOnCreate": true,
      "dependentPicklist": false,
      "deprecatedAndHidden": false,
      "digits": 0,
      "displayLocationInDecimal": false,
      "encrypted": false,
      "externalId": false,
      "extraTypeInfo": null,
      "filterable": true,
      "filteredLookupInfo": null,
      "groupable": false,
      "highScaleNumber": false,
      "htmlFormatted": false,
      "idLookup": true,
      "inlineHelpText": null,
      "label": "Name",
      "length": 255,
      "mask": null,
      "maskType": null,
      "name": "Name",
      "nameField": true,
      "namePointing": false,
      "nillable": false,
      "permissionable": false,
      "picklistValues": [],
      "precision": 0,
      "queryByDistance": false,
      "referenceTargetField": null,
      "referenceTo": [],
      "relationshipName": null,
      "relationshipOrder": null,
      "restrictedDelete": false,
      "restrictedPicklist": false,
      "scale": 0,
      "soapType": "xsd:string",
      "sortable": true,
      "type": "string",
      "unique": false,
      "updateable": false,
      "writeRequiresMasterRead": false
    },
    {
      "aggregatable": true,
      "autoNumber": false,
      "byteLength": 0,
      "calculated": false,
      "calculatedFormula": null,
      "cascadeDelete": false,
      "caseSensitive": false,
      "controllerName": null,
      "createable": false,
      "custom": false,
      "defaultValue": null,
      "defaultValueFormula": null,
      "defaultedOnCreate": true,
      "dependentPicklist": false,
      "deprecatedAndHidden": false,
      "digits": 0,
      "displayLocationInDecimal": false,
      "encrypted": false,
      "externalId": false,
      "extraTypeInfo": null,
      "filterable": true,
      "filteredLookupInfo": null,
      "groupable": false,
      "highScaleNumber": false,
      "htmlFormatted": false,
      "idLookup": false,
      "inlineHelpText": null,
      "label": "Created Date",
      "length": 0,
      "mask": null,
      "maskType": null,
      "name": "CreatedDate",
      "nameField": false,
      "namePointing": false,
      "nillable": false,
      "permissionable": false,
      "picklistValues": [],
      "precision": 0,
      "queryByDistance": false,
      "referenceTargetField": null,
      "referenceTo": [],
      "relationshipName": null,
      "relationshipOrder": null,
      "restrictedDelete": false,
      "restrictedPicklist": false,
      "scale": 0,
      "soapType": "xsd:dateTime",
      "sortable": true,
      "type": "datetime",
      "unique": false,
      "updateable": false,
      "writeRequiresMasterRead": false
    },
    {
      "aggregatable": true,
      "autoNumber": false,
      "byteLength": 18,
      "calculated": false,
      "calculatedFormula": null,
      "cascadeDelete": false,
      "caseSensitive": false,
      "controllerName": null,
      "createable": false,
      "custom": false,
      "defaultValue": null,
      "defaultValueFormula": null,
      "defaultedOnCreate": true,
      "dependentPicklist": false,
      "deprecatedAndHidden": false,
      "digits": 0,
      "displayLocationInDecimal": false,
      "encrypted": false,
      "externalId": false,
      "extraTypeInfo": null,
      "filterable": true,
      "filteredLookupInfo": null,
      "groupable": true,
      "highScaleNumber": false,
      "htmlFormatted": false,
      "idLookup": false,
      "inlineHelpText": null,
      "label": "Created By ID",
      "length": 18,
      "mask": null,
      "maskType": null,
      "name": "CreatedById",
      "nameField": false,
      "namePointing": false,
      "nillable": false,
      "permissionable": false,
      "picklistValues": [],
      "precision": 0,
      "queryByDistance": false,
      "referenceTargetField": null,
      "referenceTo": [
        "User"
      ],
      "relationshipName": "CreatedBy",
      "relationshipOrder": null,
      "restrictedDelete": false,
      "restrictedPicklist": false,
      "scale": 0,
      "soapType": "tns:ID",
      "sortable": true,
      "type": "reference",
      "unique": false,
      "updateable": false,
      "writeRequiresMasterRead": false
    },
    {
      "aggregatable": true,
      "autoNumber": false,
      "byteLength": 0,
      "calculated": false,
      "calculatedFormula": null,
      "cascadeDelete": false,
      "caseSensitive": false,
      "controllerName": null,
      "createable": false,
      "custom": false,
      "defaultValue": null,
      "defaultValueFormula": null,
      "defaultedOnCreate": true,
      "dependentPicklist": false,
      "deprecatedAndHidden": false,
      "digits": 0,
      "displayLocationInDecimal": false,
      "encrypted": false,
      "externalId": false,
      "extraTypeInfo": null,
      "filterable": true,
      "filteredLookupInfo": null,
      "groupable": false,
      "highScaleNumber": false,
      "htmlFormatted": false,
      "idLookup": false,
      "inlineHelpText": null,
      "label": "Last Modified Date",
      "length": 0,
      "mask": null,
      "maskType": null,
      "name": "LastModifiedDate",
      "nameField": false,
      "namePointing": false,
      "nillable": false,
      "permissionable": false,
      "picklistValues": [],
      "precision": 0,
      "queryByDistance": false,
      "referenceTargetField": null,
      "referenceTo": [],
      "relationshipName": null,
      "relationshipOrder": null,
      "restrictedDelete": false,
      "restrictedPicklist": false,
      "scale": 0,
      "soapType": "xsd:dateTime",
      "sortable": true,
      "type": "datetime",
      "unique": false,
      "updateable": false,
      "writeRequiresMasterRead": false
    },
    {
      "aggregatable": true,
      "autoNumber": false,
      "byteLength": 18,
      "calculated": false,
      "calculatedFormula": null,
      "cascadeDelete": false,
      "caseSensitive": false,
      "controllerName": null,
      "createable": false,
      "custom": false,
      "defaultValue": null,
      "defaultValueFormula": null,
      "defaultedOnCreate": true,
      "dependentPicklist": false,
      "deprecatedAndHidden": false,
      "digits": 0,
      "displayLocationInDecimal": false,
      "encrypted": false,
      "externalId": false,
      "extraTypeInfo": null,
      "filterable": true,
      "filteredLookupInfo": null,
      "groupable": true,
      "highScaleNumber": false,
      "htmlFormatted": false,
      "idLookup": false,
      "inlineHelpText": null,
      "label": "Last Modified By ID",
      "length": 18,
      "mask": null,
      "maskType": null,
      "name": "LastModifiedById",
      "nameField": false,
      "namePointing": false,
      "nillable": false,
      "permissionable": false,
      "picklistValues": [],
      "precision": 0,
      "queryByDistance": false,
      "referenceTargetField": null,
      "referenceTo": [
        "User"
      ],
      "relationshipName": "LastModifiedBy",
      "relationshipOrder": null,
      "restrictedDelete": false,
      "restrictedPicklist": false,
      "scale": 0,
      "soapType": "tns:ID",
      "sortable": true,
      "type": "reference",
      "unique": false,
      "updateable": false,
      "writeRequiresMasterRead": false
    },
    {
      "aggregatable": true,
      "autoNumber": false,
      "byteLength": 0,
      "calculated": false,
      "calculatedFormula": null,
      "cascadeDelete": false,
      "caseSensitive": false,
      "controllerName": null,
      "createable": false,
      "custom": false,
      "defaultValue": null,
      "defaultValueFormula": null,
      "defaultedOnCreate": true,
      "dependentPicklist": false,
      "deprecatedAndHidden": false,
      "digits": 0,
      "displayLocationInDecimal": false,
      "encrypted": false,
      "externalId": false,
      "extraTypeInfo": null,
      "filterable": true,
      "filteredLookupInfo": null,
      "groupable": false,
      "highScaleNumber": false,
      "htmlFormatted": false,
      "idLookup": false,
      "inlineHelpText": null,
      "label": "System Modstamp",
      "length": 0,
      "mask": null,
      "maskType": null,
      "name": "SystemModstamp",
      "nameField": false,
      "namePointing": false,
      "nillable": false,
      "permissionable": false,
      "picklistValues": [],
      "precision": 0,
      "queryByDistance": false,
      "referenceTargetField": null,
      "referenceTo": [],
      "relationshipName": null,
      "relationshipOrder": null,
      "restrictedDelete": false,
      "restrictedPicklist": false,
      "scale": 0,
      "soapType": "xsd:dateTime",
      "sortable": true,
      "type": "datetime",
      "unique": false,
      "updateable": false,
      "writeRequiresMasterRead": false
    },
    {
      "aggregatable": true,
      "autoNumber": false,
      "byteLength": 0,
      "calculated": false,
      "calculatedFormula": null,
      "cascadeDelete": false,
      "caseSensitive": false,
      "controllerName": null,
      "createable": true,
      "custom": false,
      "defaultValue": null,
      "defaultValueFormula": null,
      "defaultedOnCreate": false,
      "dependentPicklist": false,
      "deprecatedAndHidden": false,
      "digits": 0,
      "displayLocationInDecimal": false,
      "encrypted": false,
      "externalId": false,
      "extraTypeInfo": null,
      "filterable": true,
      "filteredLookupInfo": null,
      "groupable": false,
      "highScaleNumber": false,
      "htmlFormatted": false,
      "idLookup": false,
      "inlineHelpText": null,
      "label": "Value",
      "length": 0,
      "mask": null,
      "maskType": null,
      "name": "Value",
      "nameField": false,
      "namePointing": false,
      "nillable": true,
      "permissionable": false,
      "picklistValues": [],
      "precision": 18,
      "queryByDistance": false,
      "referenceTargetField": null,
      "referenceTo": [],
      "relationshipName": null,
      "relationshipOrder": null,
      "restrictedDelete": false,
      "restrictedPicklist": false,
      "scale": 0,
      "soapType": "xsd:double",
      "sortable": true,
      "type": "currency",
      "unique": false,
      "updateable": true,
      "writeRequiresMasterRead": false
    },
    {
      "aggregatable": true,
      "autoNumber": false,
      "byteLength": 18,
      "calculated": false,
      "calculatedFormula": null,
      "cascadeDelete": false,
      "caseSensitive": false,
      "controllerName": null,
      "createable": true,
      "custom": false,
      "defaultValue": null,
      "defaultValueFormula": null,
      "defaultedOnCreate": false,
      "dependentPicklist": false,
      "deprecatedAndHidden": false,
      "digits": 0,
      "displayLocationInDecimal": false,
      "encrypted": false,
      "externalId": false,
      "extraTypeInfo": null,
      "filterable": true,
      "filteredLookupInfo": null,
      "groupable": true,
      "highScaleNumber": false,
      "htmlFormatted": false,
      "idLookup": false,
      "inlineHelpText": null,
      "label": "User ID",
      "length": 18,
      "mask": null,
      "maskType": null,
      "name": "UserId",
      "nameField": false,
      "namePointing": false,
      "nillable": false,
      "permissionable": false,
      "picklistValues": [],
      "precision": 0,
      "queryByDistance": false,
      "referenceTargetField": null,
      "referenceTo": [
        "User"
      ],
      "relationshipName": "User",
      "relationshipOrder": null,
      "restrictedDelete": false,
      "restrictedPicklist": false,
      "scale": 0,
      "soapType": "tns:ID",
      "sortable": true,
      "type": "reference",
      "unique": true,
      "updateable": true,
      "writeRequiresMasterRead": false
    }
  ],
  "keyPrefix": "0Jz",
  "label": "Goal",
  "labelPlural": "Goals",
  "layoutable": false,
  "listviewable": null,
  "lookupLayoutable": null,
  "mergeable": false,
  "mruEnabled": false,
  "name": "TodayGoal",
  "namedLayoutInfos": [],
  "networkScopeFieldName": null,
  "queryable": true,
  "recordTypeInfos": [],
  "replicateable": true,
  "retrieveable": true,
  "searchLayoutable": false,
  "searchable": false,
  "supportedScopes": [
    {
      "label": "All goals",
      "name": "everything"
    },
    {
      "label": "My goals",
      "name": "mine"
    },
    {
      "label": "Queue owned goals",
      "name": "queue_owned"
    },
    {
      "label": "My team's goals",
      "name": "team"
    },
    {
      "label": "User owned goals",
      "name": "user_owned"
    }
  ],
  "triggerable": false,
  "undeletable": true,
  "updateable": true,
  "urls": {
    "compactLayouts": null,
    "rowTemplate": "/services/data/v40.0/sobjects/TodayGoal/{ID}",
    "approvalLayouts": null,
    "uiDetailTemplate": null,
    "uiEditTemplate": null,
    "defaultValues": "/services/data/v40.0/sobjects/TodayGoal/defaultValues?recordTypeId&fields",
    "describe": "/services/data/v40.0/sobjects/TodayGoal/describe",
    "uiNewRecord": null,
    "quickActions": null,
    "layouts": null,
    "sobject": "/services/data/v40.0/sobjects/TodayGoal"
  }
}